reotp/__init__.py
reotp/__main__.py
reotp/otp_schema.proto
reotp/pbotp.py
reotp-0.2.0.dist-info/METADATA
reotp-0.2.0.dist-info/WHEEL
reotp-0.2.0.dist-info/entry_points.txt
reotp-0.2.0.dist-info/licenses/LICENSE.md
reotp-0.2.0.dist-info/RECORD
