Metadata-Version: 2.4
Name: reotp
Version: 0.2.0
Summary: Regenerate OTP URIs and QR Codes
Project-URL: Homepage, https://github.com/cbinckly/reotp
Project-URL: Bug Tracker, https://github.com/cbinckly/reotp/issues
Author-email: Chris Binckly <cbinckly@gmail.com>
License-File: LICENSE.md
Classifier: Operating System :: OS Independent
Classifier: Programming Language :: Python :: 3
Requires-Python: >=3.10
Requires-Dist: pyotp
Requires-Dist: qrcode[pil]
